Metadata-Version: 2.1
Name: odoo13-addon-sale-order-product-availability-inline
Version: 13.0.1.1.1
Summary: Show product availability in sales order line product drop-down.
Home-page: https://github.com/OCA/sale-workflow
Author: Tecnativa, Odoo Community Association (OCA)
Author-email: support@odoo-community.org
License: AGPL-3
Platform: UNKNOWN
Classifier: Programming Language :: Python
Classifier: Framework :: Odoo
Classifier: License :: OSI Approved :: GNU Affero General Public License v3
Classifier: Development Status :: 4 - Beta
Requires-Python: >=3.5
Requires-Dist: odoo13-addon-base-view-inheritance-extension
Requires-Dist: odoo (<13.1dev,>=13.0a)
